setup.py
pywx1/__init__.py
pywx1/cli.py
pywx1.egg-info/PKG-INFO
pywx1.egg-info/SOURCES.txt
pywx1.egg-info/dependency_links.txt
pywx1.egg-info/entry_points.txt
pywx1.egg-info/not-zip-safe
pywx1.egg-info/top_level.txt