Metadata-Version: 1.1
Name: pywx1
Version: 0.0.2
Summary: pywx1
Home-page: https://github.com/hustcc/hust
Author: hustcc
Author-email: i@hust.cc
License: MIT
Keywords: pywx1,hustcc,github
Platform: UNKNOWN
Classifier: Intended Audience :: Developers
Classifier: Operating System :: OS Independent
Classifier: Natural Language :: Chinese (Simplified)
Classifier: Programming Language :: Python
Classifier: Programming Language :: Python :: 3
Classifier: Programming Language :: Python :: 3.6
Classifier: Topic :: Utilities
